pygraphic/__init__.py
pygraphic/_gql_enum.py
pygraphic/_gql_query.py
pygraphic/_gql_type.py
pygraphic/_gql_variables.py
pygraphic/exceptions.py
pygraphic/py.typed
pygraphic/serializers.py
pygraphic-0.5.dist-info/LICENSE
pygraphic-0.5.dist-info/WHEEL
pygraphic-0.5.dist-info/METADATA
pygraphic-0.5.dist-info/RECORD
