Metadata-Version: 2.1
Name: pygraphic
Version: 0.5
Summary: Client-side GraphQL query generator based on Pydantic
Home-page: https://github.com/lonelyteapot/pygraphic
License: MIT
Keywords: graphql-query-generator,graphql-codegen,graphql,query,pydantic
Author: Dmitry Semenov
Author-email: lonelyteapot@gmail.com
Requires-Python: >=3.10,<4.0
Classifier: Development Status :: 4 - Beta
Classifier: Intended Audience :: Developers
Classifier: License :: OSI Approved :: MIT License
Classifier: Programming Language :: Python :: 3
Classifier: Programming Language :: Python :: 3.10
Classifier: Topic :: Software Development :: Libraries
Classifier: Topic :: Software Development :: Libraries :: Python Modules
Classifier: Typing :: Typed
Requires-Dist: inflection (>=0.5.1,<0.6.0)
Requires-Dist: pydantic (>=1.9.1,<2.0.0)
Project-URL: Examples, https://github.com/lonelyteapot/pygraphic/tree/main/examples
Project-URL: Repository, https://github.com/lonelyteapot/pygraphic
